pgmigrate.py
yandex_pgmigrate-1.0.10.dist-info/licenses/AUTHORS
yandex_pgmigrate-1.0.10.dist-info/licenses/LICENSE
yandex_pgmigrate-1.0.10.dist-info/METADATA
yandex_pgmigrate-1.0.10.dist-info/WHEEL
yandex_pgmigrate-1.0.10.dist-info/entry_points.txt
yandex_pgmigrate-1.0.10.dist-info/top_level.txt
yandex_pgmigrate-1.0.10.dist-info/RECORD
