Metadata-Version: 2.4
Name: yandex-pgmigrate
Version: 1.0.10
Summary: PostgreSQL migrations made easy
Home-page: https://github.com/yandex/pgmigrate/
Author: Yandex LLC
Author-email: opensource@yandex-team.ru
Maintainer: Yandex LLC
Maintainer-email: opensource@yandex-team.ru
License: PostgreSQL License
Platform: Linux
Platform: BSD
Platform: MacOS
License-File: LICENSE
License-File: AUTHORS
Requires-Dist: sqlparse>=0.3.0
Requires-Dist: psycopg2>=2.8.2
Requires-Dist: PyYAML>=5.2
Dynamic: author
Dynamic: author-email
Dynamic: description
Dynamic: description-content-type
Dynamic: home-page
Dynamic: license
Dynamic: license-file
Dynamic: maintainer
Dynamic: maintainer-email
Dynamic: platform
Dynamic: requires-dist
Dynamic: summary
